COPYING
INSTALL
MANIFEST.in
README.rst
setup.py
pyrtist/__init__.py
pyrtist/__main__.py
pyrtist.egg-info/PKG-INFO
pyrtist.egg-info/SOURCES.txt
pyrtist.egg-info/dependency_links.txt
pyrtist.egg-info/entry_points.txt
pyrtist.egg-info/top_level.txt
pyrtist/examples/arcs.py
pyrtist/examples/bar.py
pyrtist/examples/cairo_gradient.py
pyrtist/examples/constraints.py
pyrtist/examples/curve.png
pyrtist/examples/fractal.box
pyrtist/examples/fractree.box
pyrtist/examples/gradient.py
pyrtist/examples/house.py
pyrtist/examples/planes.py
pyrtist/examples/surf_charges.py
pyrtist/examples/tutorial02-polygons.py
pyrtist/examples/tutorial03-curved_polys.py
pyrtist/examples/tutorial99-various.py
pyrtist/examples/wheatstone.box
pyrtist/gui/__init__.py
pyrtist/gui/assistant.py
pyrtist/gui/base.py
pyrtist/gui/boxmode.py
pyrtist/gui/callbacks.py
pyrtist/gui/colortool.py
pyrtist/gui/config.py
pyrtist/gui/document.py
pyrtist/gui/editable.py
pyrtist/gui/fonttool.py
pyrtist/gui/geom2.py
pyrtist/gui/info.py
pyrtist/gui/inputtool.py
pyrtist/gui/mainwindow.py
pyrtist/gui/namegen.py
pyrtist/gui/pydraw.py
pyrtist/gui/refpoints.py
pyrtist/gui/renderer.py
pyrtist/gui/rotpaned.py
pyrtist/gui/scriptrunner.py
pyrtist/gui/srcview.py
pyrtist/gui/toolbox.py
pyrtist/gui/undoer.py
pyrtist/gui/zoomable.py
pyrtist/gui/comparse/__init__.py
pyrtist/gui/comparse/comparse.py
pyrtist/gui/comparse/textslice.py
pyrtist/gui/dox/__init__.py
pyrtist/gui/dox/block.py
pyrtist/gui/dox/browse.py
pyrtist/gui/dox/builder.py
pyrtist/gui/dox/context.py
pyrtist/gui/dox/dox.py
pyrtist/gui/dox/extractor.py
pyrtist/gui/dox/gtktext.py
pyrtist/gui/dox/logger.py
pyrtist/gui/dox/rst.py
pyrtist/gui/dox/rstparser.py
pyrtist/gui/dox/tree.py
pyrtist/gui/dox/writer.py
pyrtist/icons/24x24/border.png
pyrtist/icons/24x24/borderds.png
pyrtist/icons/24x24/borderwd.png
pyrtist/icons/24x24/caparrow.png
pyrtist/icons/24x24/capcircle.png
pyrtist/icons/24x24/caplarr.png
pyrtist/icons/24x24/capruler.png
pyrtist/icons/24x24/captriang.png
pyrtist/icons/24x24/circgrad.png
pyrtist/icons/24x24/circle.png
pyrtist/icons/24x24/circleradius.png
pyrtist/icons/24x24/color.png
pyrtist/icons/24x24/colornew.png
