Metadata-Version: 1.1
Name: pyrtist
Version: 0.0.3
Summary: A GUI which enables drawing using Python scripts
Home-page: https://github.com/mfnch/pyrtist
Author: Matteo Franchin
Author-email: fnch@users.sf.net
License: LGPL
Platform: UNKNOWN
Classifier: Programming Language :: Python :: 2
Classifier: Programming Language :: Python :: 2.7
Classifier: Development Status :: 3 - Alpha
Classifier: Topic :: Multimedia :: Graphics :: Editors :: Vector-Based
Classifier: License :: OSI Approved :: GNU Lesser General Public License v2 or later (LGPLv2+)
